[
    {
        "id": "307",
        "nom": "BREZONS - ROCHER DE LA BOYLE (S)",
        "code": "307",
        "commune": "BREZONS",
        "code_postal": "15230",
        "activite": "parapente delta  [ déco ]",
        "statut": "actif",
        "latitude": 45.0065,
        "longitude": 2.8135,
        "altitude": 1287,
        "secteurs_vent": "S;SOSecteurs de vent défavorables : N;NE;E;SE;NOConditions aérologiques idéales : Léger SO , conditions thermiques, restitution",
        "orientation_all": "S;SO",
        "orientation": "S"
    },
    {
        "id": "487",
        "nom": "CHABRAIRE (NO)",
        "code": "487",
        "commune": "LE CLAUX",
        "code_postal": "15400",
        "activite": "parapente delta  [ déco ]",
        "statut": "actif",
        "latitude": 45.1565,
        "longitude": 2.7326,
        "altitude": 1522,
        "secteurs_vent": "N;O;NOSecteurs de vent défavorables : NE;E;SE;S;SOConditions aérologiques idéales : Non renseigné",
        "orientation_all": "N;O;NO",
        "orientation": "NO"
    },
    {
        "id": "292",
        "nom": "COL-D 'AULAC (S)",
        "code": "292",
        "commune": "LE VAULMIER",
        "code_postal": "15380",
        "activite": "parapente delta  [ déco ]",
        "statut": "actif",
        "latitude": 45.194,
        "longitude": 2.5812,
        "altitude": 1190,
        "secteurs_vent": "SE;S;SOSecteurs de vent défavorables : N;NE;E;NOConditions aérologiques idéales : vent faible",
        "orientation_all": "SE;S;SO",
        "orientation": "S"
    },
    {
        "id": "1947",
        "nom": "DIENNE EMBEC (E)",
        "code": "1947",
        "commune": "DIENNE",
        "code_postal": "15300",
        "activite": "parapente  [ déco ]",
        "statut": "actif",
        "latitude": 45.1612,
        "longitude": 2.772,
        "altitude": 1427,
        "secteurs_vent": "NE;E;SESecteurs de vent défavorables : S;SO;O;NOConditions aérologiques idéales : Vent du secteur Est faible",
        "orientation_all": "NE;E;SE",
        "orientation": "E"
    },
    {
        "id": "2357",
        "nom": "ENGOLNEUF (NO)",
        "code": "2357",
        "commune": "DIENNE",
        "code_postal": "15300",
        "activite": "parapente delta  [ déco ]",
        "statut": "actif",
        "latitude": 45.133,
        "longitude": 2.7887,
        "altitude": 1447,
        "secteurs_vent": "N;NE;O;NOSecteurs de vent défavorables : E;SE;S;SOConditions aérologiques idéales : Vent léger NO ou conditions thermique de l'après midi, restitution",
        "orientation_all": "N;NE;O;NO",
        "orientation": "NO"
    },
    {
        "id": "5028",
        "nom": "LES BLATTES",
        "code": "5028",
        "commune": "VIC-SUR-CERE",
        "code_postal": "15800",
        "activite": "parapente  [ déco ]",
        "statut": "actif",
        "latitude": 44.9866,
        "longitude": 2.606,
        "altitude": 1098,
        "secteurs_vent": "Non renseignéSecteurs de vent défavorables : Non renseignéConditions aérologiques idéales : Non renseigné",
        "orientation_all": "Non renseigné",
        "orientation": null
    },
    {
        "id": "303",
        "nom": "PIERRE-DE-LABRO - NOZIERES (SE)",
        "code": "303",
        "commune": "DIENNE",
        "code_postal": "15300",
        "activite": "parapente delta  [ déco ]",
        "statut": "actif",
        "latitude": 45.169,
        "longitude": 2.7943,
        "altitude": 1314,
        "secteurs_vent": "E;SE;SSecteurs de vent défavorables : N;NE;SO;O;NOConditions aérologiques idéales : Leger vent SE (20km/h)",
        "orientation_all": "E;SE;S",
        "orientation": "SE"
    },
    {
        "id": "479",
        "nom": "PLOMB DU CANTAL (NO)",
        "code": "479",
        "commune": "LAVEISSIERE",
        "code_postal": "15300",
        "activite": "parapente delta  [ déco ]",
        "statut": "actif",
        "latitude": 45.0626,
        "longitude": 2.7601,
        "altitude": 1803,
        "secteurs_vent": "N;O;NOSecteurs de vent défavorables : NE;E;SE;SConditions aérologiques idéales : Non renseigné",
        "orientation_all": "N;O;NO",
        "orientation": "NO"
    },
    {
        "id": "480",
        "nom": "PUY BRUNET - CRETE DU PLOMB 2 (SO)",
        "code": "480",
        "commune": "ST JACQUES DES BLATS",
        "code_postal": "15800",
        "activite": "parapente delta  [ déco ]",
        "statut": "actif",
        "latitude": 45.0607,
        "longitude": 2.7609,
        "altitude": 1812,
        "secteurs_vent": "N;SE;S;SO;OSecteurs de vent défavorables : NE;EConditions aérologiques idéales : Non renseigné",
        "orientation_all": "N;SE;S;SO;O",
        "orientation": "SO"
    },
    {
        "id": "1030",
        "nom": "PUY- DE-LA-TOURTE - NORD-EST (NE)",
        "code": "1030",
        "commune": "LE CLAUX",
        "code_postal": "15400",
        "activite": "parapente delta  [ déco ]",
        "statut": "actif",
        "latitude": 45.1264,
        "longitude": 2.6746,
        "altitude": 1649,
        "secteurs_vent": "NESecteurs de vent défavorables : Non renseignéConditions aérologiques idéales : Non renseigné",
        "orientation_all": "NE",
        "orientation": "NE"
    },
    {
        "id": "1027",
        "nom": "PUY-DE-LA-TOURTE-OUEST (O)",
        "code": "1027",
        "commune": "LE FALGOUX",
        "code_postal": "15380",
        "activite": "parapente delta  [ déco ]",
        "statut": "actif",
        "latitude": 45.1258,
        "longitude": 2.6742,
        "altitude": 1648,
        "secteurs_vent": "OSecteurs de vent défavorables : Non renseignéConditions aérologiques idéales : Non renseigné",
        "orientation_all": "O",
        "orientation": "O"
    },
    {
        "id": "1048",
        "nom": "PUY-MARY - NORD-EST - PAS-DE-PEYROL (NE)",
        "code": "1048",
        "commune": "LE CLAUX",
        "code_postal": "15400",
        "activite": "parapente delta  [ déco ]",
        "statut": "actif",
        "latitude": 45.1165,
        "longitude": 2.6711,
        "altitude": 871,
        "secteurs_vent": "NESecteurs de vent défavorables : Non renseignéConditions aérologiques idéales : Non renseigné",
        "orientation_all": "NE",
        "orientation": "NE"
    },
    {
        "id": "1032",
        "nom": "PUY-MARY - SUD - COL-DU-REDONDET (S)",
        "code": "1032",
        "commune": "MANDAILLES - ST JULIEN",
        "code_postal": "15590",
        "activite": "parapente delta  [ déco ]",
        "statut": "actif",
        "latitude": 45.1056,
        "longitude": 2.6608,
        "altitude": 1503,
        "secteurs_vent": "SSecteurs de vent défavorables : Non renseignéConditions aérologiques idéales : Non renseigné",
        "orientation_all": "S",
        "orientation": "S"
    },
    {
        "id": "2356",
        "nom": "ROCHER-DE-LAQUEUILLE (O)",
        "code": "2356",
        "commune": "DIENNE",
        "code_postal": "15300",
        "activite": "parapente  [ déco ]",
        "statut": "actif",
        "latitude": 45.1484,
        "longitude": 2.7903,
        "altitude": 1250,
        "secteurs_vent": "OSecteurs de vent défavorables : N;NE;E;SE;S;SOConditions aérologiques idéales : Vent de Ouest leger",
        "orientation_all": "O",
        "orientation": "O"
    },
    {
        "id": "305",
        "nom": "ROCHER-DE-LAQUEUILLE-NE (NE)",
        "code": "305",
        "commune": "DIENNE",
        "code_postal": "15300",
        "activite": "parapente delta  [ déco ]",
        "statut": "actif",
        "latitude": 45.1485,
        "longitude": 2.7945,
        "altitude": 1262,
        "secteurs_vent": "NESecteurs de vent défavorables : SE;S;SO;O;NOConditions aérologiques idéales : Vent NE leger",
        "orientation_all": "NE",
        "orientation": "NE"
    },
    {
        "id": "5116",
        "nom": "SENERGUES (O)",
        "code": "5116",
        "commune": "VIEILLEVIE",
        "code_postal": "15120",
        "activite": "parapente  [ déco ]",
        "statut": "actif",
        "latitude": 44.6374,
        "longitude": 2.452,
        "altitude": 591,
        "secteurs_vent": "O;NO;Secteurs de vent défavorables : Non renseignéConditions aérologiques idéales : Non renseigné",
        "orientation_all": "O;NO;",
        "orientation": "O"
    },
    {
        "id": "310",
        "nom": "VIC-SUR-CERE - LE-BRUGET (O)",
        "code": "310",
        "commune": "VIC SUR CERE",
        "code_postal": "15800",
        "activite": "parapente delta  [ déco ]",
        "statut": "actif",
        "latitude": 44.982,
        "longitude": 2.659,
        "altitude": 1113,
        "secteurs_vent": "SO;O;NOSecteurs de vent défavorables : NE;E;SE;SConditions aérologiques idéales : vent faible ou modéré de ouest",
        "orientation_all": "SO;O;NO",
        "orientation": "O"
    }
]