[
    {
        "id": "1893",
        "nom": "AIGLE - LANS EN VERCORS",
        "code": "1893",
        "commune": "LANS EN VERCORS",
        "code_postal": "38250",
        "activite": "parapente delta cerf-volant boomerang  [ atterro ]",
        "statut": "actif"
    },
    {
        "id": "1892",
        "nom": "AIGLE - LANS EN VERCORS - SOMMET",
        "code": "1892",
        "commune": "LANS EN VERCORS",
        "code_postal": "38250",
        "activite": "parapente delta  [ déco ]",
        "statut": "actif"
    },
    {
        "id": "13194",
        "nom": "ALPE D 'HUEZ - BOURG D 'OISANS",
        "code": "13194",
        "commune": "ALPE D'HUEZ",
        "code_postal": "38750",
        "activite": "parapente  [ atterro pente école ]",
        "statut": "actif"
    },
    {
        "id": "2342",
        "nom": "ALPE D 'HUEZ - BOURG D 'OISANS - 2700",
        "code": "2342",
        "commune": "ALPE D'HUEZ",
        "code_postal": "38750",
        "activite": "parapente  [ déco ]",
        "statut": "actif"
    },
    {
        "id": "2344",
        "nom": "ALPE D 'HUEZ - BOURG D 'OISANS - CLOCHER DE MACLE",
        "code": "2344",
        "commune": "ALPE D'HUEZ",
        "code_postal": "38750",
        "activite": "parapente  [ déco ]",
        "statut": "actif"
    },
    {
        "id": "1923",
        "nom": "ALPE D 'HUEZ - BOURG D 'OISANS - ECLOSE",
        "code": "1923",
        "commune": "HUEZ",
        "code_postal": "38750",
        "activite": "parapente delta  [ déco ]",
        "statut": "actif"
    },
    {
        "id": "1924",
        "nom": "ALPE D 'HUEZ - BOURG D 'OISANS - LA MINARDIERE",
        "code": "1924",
        "commune": "BOURG D'OISANS",
        "code_postal": "38520",
        "activite": "parapente delta  [ atterro ]",
        "statut": "actif"
    },
    {
        "id": "2341",
        "nom": "ALPE D 'HUEZ - BOURG D 'OISANS - LE SIGNAL",
        "code": "2341",
        "commune": "ALPE D'HUEZ",
        "code_postal": "38750",
        "activite": "parapente delta  [ déco ]",
        "statut": "actif"
    },
    {
        "id": "13473",
        "nom": "ALPE D 'HUEZ - BOURG D 'OISANS - LE VERT",
        "code": "13473",
        "commune": "BOURG D'OISANS",
        "code_postal": "38520",
        "activite": "parapente  [ atterro ]",
        "statut": "actif"
    },
    {
        "id": "13204",
        "nom": "ALPE D 'HUEZ - BOURG D 'OISANS - POUTRAN",
        "code": "13204",
        "commune": "ALPE D'HUEZ",
        "code_postal": "38750",
        "activite": "parapente  [ atterro ]",
        "statut": "actif"
    },
    {
        "id": "13499",
        "nom": "ALPE D 'HUEZ - BOURG D 'OISANS - STADE MUNICIPAL",
        "code": "13499",
        "commune": "BOURG D'OISANS",
        "code_postal": "38520",
        "activite": "parapente  [ atterro ]",
        "statut": "actif"
    },
    {
        "id": "2343",
        "nom": "ALPE D 'HUEZ - BOURG D 'OISANS - STATION 1800 - ROND POINT DES PISTES",
        "code": "2343",
        "commune": "ALPE D'HUEZ",
        "code_postal": "38750",
        "activite": "parapente delta  [ atterro ]",
        "statut": "actif"
    },
    {
        "id": "1815",
        "nom": "AUTRANS BELLECOMBE",
        "code": "1815",
        "commune": "AUTRANS",
        "code_postal": "38880",
        "activite": "parapente  [ déco ]",
        "statut": "actif"
    },
    {
        "id": "1817",
        "nom": "AUTRANS BELLECOMBE - LE BOUCHET - SECOURS",
        "code": "1817",
        "commune": "AUTRANS",
        "code_postal": "38880",
        "activite": "parapente  [ atterro ]",
        "statut": "actif"
    },
    {
        "id": "1816",
        "nom": "AUTRANS BELLECOMBE - LE VILLAGE",
        "code": "1816",
        "commune": "AUTRANS",
        "code_postal": "38880",
        "activite": "parapente  [ atterro ]",
        "statut": "actif"
    },
    {
        "id": "13715",
        "nom": "BELVEDERE (LANS) - BELVE - LES BLANCS",
        "code": "13715",
        "commune": "LANS EN VERCORS",
        "code_postal": "38250",
        "activite": "parapente  [ déco ]",
        "statut": "actif"
    },
    {
        "id": "324",
        "nom": "CHALAIS",
        "code": "324",
        "commune": "VOREPPE",
        "code_postal": "38340",
        "activite": "parapente  [ déco ]",
        "statut": "actif"
    },
    {
        "id": "2315",
        "nom": "CHALAIS - RESERVE PMR",
        "code": "2315",
        "commune": "VOREPPE",
        "code_postal": "38340",
        "activite": "parapente  [ déco ]",
        "statut": "actif"
    },
    {
        "id": "13148",
        "nom": "CHALAIS - TERRAIN RUGBY - SECOURS",
        "code": "13148",
        "commune": "VOREPPE",
        "code_postal": "38340",
        "activite": "parapente  [ atterro ]",
        "statut": "actif"
    },
    {
        "id": "325",
        "nom": "CHALAIS - VOREPPE RIVALIERES",
        "code": "325",
        "commune": "VOREPPE",
        "code_postal": "38340",
        "activite": "parapente  [ atterro ]",
        "statut": "actif"
    },
    {
        "id": "5260",
        "nom": "CHAMECHAUDE",
        "code": "5260",
        "commune": "SARCENAS",
        "code_postal": "38700",
        "activite": "parapente  [ déco ]",
        "statut": "actif"
    },
    {
        "id": "1025",
        "nom": "CHAMROUSSE - L 'AIGUILLE",
        "code": "1025",
        "commune": "CHAMROUSSE",
        "code_postal": "38410",
        "activite": "parapente delta  [ déco atterro ]",
        "statut": "actif"
    },
    {
        "id": "1026",
        "nom": "CHAMROUSSE - LA RICHARDIERE",
        "code": "1026",
        "commune": "URIAGE",
        "code_postal": "38410",
        "activite": "parapente  [ atterro ]",
        "statut": "actif"
    },
    {
        "id": "1908",
        "nom": "CHAMROUSSE - SPEED-RIDING",
        "code": "1908",
        "commune": "CHAMROUSSE",
        "code_postal": "38410",
        "activite": "speedriding  [ ]",
        "statut": "actif"
    },
    {
        "id": "5301",
        "nom": "CHARANDE",
        "code": "5301",
        "commune": "ENGINS",
        "code_postal": "38360",
        "activite": "parapente  [ déco ]",
        "statut": "actif"
    },
    {
        "id": "5119",
        "nom": "CHARMANT SOM",
        "code": "5119",
        "commune": "SAINT-PIERRE-DE-CHARTREUSE",
        "code_postal": "38380",
        "activite": "parapente  [ déco ]",
        "statut": "actif"
    },
    {
        "id": "136",
        "nom": "COGNIN - LA LIA",
        "code": "136",
        "commune": "COGNIN LES GORGES",
        "code_postal": "38470",
        "activite": "parapente  [ atterro ]",
        "statut": "actif"
    },
    {
        "id": "5306",
        "nom": "COL DE BAURE",
        "code": "5306",
        "commune": "SAINT-PANCRASSE",
        "code_postal": "38660",
        "activite": "parapente  [ déco ]",
        "statut": "interdit"
    },
    {
        "id": "5263",
        "nom": "COL DE L 'ARC",
        "code": "5263",
        "commune": "SAINT-PAUL-DE-VARCES",
        "code_postal": "38760",
        "activite": "parapente  [ déco ]",
        "statut": "actif"
    },
    {
        "id": "3079",
        "nom": "COL DU SABOT",
        "code": "3079",
        "commune": "VAUJANY",
        "code_postal": "38114",
        "activite": "parapente  [ déco ]",
        "statut": "actif"
    },
    {
        "id": "5303",
        "nom": "COL DU VALLON",
        "code": "5303",
        "commune": "VENOSC",
        "code_postal": "38520",
        "activite": "parapente  [ atterro ]",
        "statut": "actif"
    },
    {
        "id": "5122",
        "nom": "COL VERT",
        "code": "5122",
        "commune": "LE GUA",
        "code_postal": "38450",
        "activite": "parapente  [ déco ]",
        "statut": "actif"
    },
    {
        "id": "684",
        "nom": "COLLET D 'ALLEVARD - LA DIGUE",
        "code": "684",
        "commune": "ALLEVARD",
        "code_postal": "38580",
        "activite": "parapente  [ atterro ]",
        "statut": "actif"
    },
    {
        "id": "685",
        "nom": "COLLET D 'ALLEVARD - LA MIRANDE",
        "code": "685",
        "commune": "ALLEVARD",
        "code_postal": "38580",
        "activite": "parapente  [ atterro ]",
        "statut": "non praticable définitivement"
    },
    {
        "id": "686",
        "nom": "COLLET D 'ALLEVARD - LES PLAGNES",
        "code": "686",
        "commune": "ALLEVARD",
        "code_postal": "38580",
        "activite": "parapente delta  [ déco ]",
        "statut": "actif"
    },
    {
        "id": "682",
        "nom": "COLLET D 'ALLEVARD - MALATRAIT",
        "code": "682",
        "commune": "ALLEVARD",
        "code_postal": "38580",
        "activite": "parapente delta  [ déco ]",
        "statut": "actif"
    },
    {
        "id": "683",
        "nom": "COLLET D 'ALLEVARD - NID D 'AIGLE",
        "code": "683",
        "commune": "ALLEVARD",
        "code_postal": "38580",
        "activite": "parapente delta  [ déco ]",
        "statut": "actif"
    },
    {
        "id": "13415",
        "nom": "COLLET D 'ALLEVARD - PRE ROND",
        "code": "13415",
        "commune": "LA CHAPELLE DU BARD",
        "code_postal": "38580",
        "activite": "parapente delta  [ déco ]",
        "statut": "actif"
    },
    {
        "id": "13412",
        "nom": "COLLET D 'ALLEVARD - SUD",
        "code": "13412",
        "commune": "ALLEVARD",
        "code_postal": "38580",
        "activite": "parapente delta  [ déco ]",
        "statut": "actif"
    },
    {
        "id": "13416",
        "nom": "COLLET D 'ALLEVARD - SUPER-COLLET",
        "code": "13416",
        "commune": "LA CHAPELLE DU BARD",
        "code_postal": "38580",
        "activite": "parapente delta  [ atterro ]",
        "statut": "actif"
    },
    {
        "id": "350",
        "nom": "COLOMBIERS",
        "code": "350",
        "commune": "VALBONNAIS",
        "code_postal": "38740",
        "activite": "parapente delta  [ déco ]",
        "statut": "actif"
    },
    {
        "id": "351",
        "nom": "COLOMBIERS - ENTRAIGUES",
        "code": "351",
        "commune": "ENTRAIGUES",
        "code_postal": "38740",
        "activite": "parapente delta  [ atterro ]",
        "statut": "actif"
    },
    {
        "id": "13626",
        "nom": "COMBERON - LE RAZIER",
        "code": "13626",
        "commune": "SAINT AREY",
        "code_postal": "38350",
        "activite": "parapente  [ déco ]",
        "statut": "actif autorisation systematique requise"
    },
    {
        "id": "3038",
        "nom": "COMBOURSIERE",
        "code": "3038",
        "commune": "SAINT-HONORE",
        "code_postal": "38350",
        "activite": "parapente  [ déco ]",
        "statut": "actif"
    },
    {
        "id": "193",
        "nom": "CONNEX",
        "code": "193",
        "commune": "NOTRE DAME DE VAUX",
        "code_postal": "38144",
        "activite": "parapente delta  [ déco ]",
        "statut": "actif"
    },
    {
        "id": "194",
        "nom": "CONNEX",
        "code": "194",
        "commune": "NOTRE DAME DE VAUX",
        "code_postal": "38350",
        "activite": "parapente delta  [ atterro ]",
        "statut": "actif"
    },
    {
        "id": "5270",
        "nom": "CORRENCON-BELVE",
        "code": "5270",
        "commune": "CORRENCON EN VERCOS",
        "code_postal": "38250",
        "activite": "parapente  [ déco ]",
        "statut": "actif"
    },
    {
        "id": "14215",
        "nom": "CORRENCON-BELVE",
        "code": "14215",
        "commune": "CORRENCON EN VERCOS",
        "code_postal": "38250",
        "activite": "parapente  [ atterro ]",
        "statut": "actif"
    },
    {
        "id": "3049",
        "nom": "COTE ROTTE",
        "code": "3049",
        "commune": "VILLARD-SAINT-CHRISTOPHE",
        "code_postal": "38119",
        "activite": "parapente  [ déco ]",
        "statut": "actif"
    },
    {
        "id": "13371",
        "nom": "COTE2000 PRE DE L 'ACHARD",
        "code": "13371",
        "commune": "VILLARD DE LANS",
        "code_postal": "38250",
        "activite": "parapente  [ déco ]",
        "statut": "actif"
    },
    {
        "id": "854",
        "nom": "COURTET",
        "code": "854",
        "commune": "ST BAUDILLE",
        "code_postal": "38710",
        "activite": "parapente delta  [ déco ]",
        "statut": "actif"
    },
    {
        "id": "855",
        "nom": "COURTET",
        "code": "855",
        "commune": "ST BAUDILLE",
        "code_postal": "38710",
        "activite": "parapente delta  [ atterro ]",
        "statut": "actif"
    },
    {
        "id": "959",
        "nom": "COURTET",
        "code": "959",
        "commune": "MENS",
        "code_postal": "38710",
        "activite": "parapente delta  [ atterro ]",
        "statut": "actif"
    },
    {
        "id": "5121",
        "nom": "CROIX DE CHAMROUSSE",
        "code": "5121",
        "commune": "CHAMROUSSE",
        "code_postal": "38220",
        "activite": "parapente  [ déco ]",
        "statut": "actif"
    },
    {
        "id": "5259",
        "nom": "GRAND COLON",
        "code": "5259",
        "commune": "REVEL",
        "code_postal": "38420",
        "activite": "parapente  [ déco ]",
        "statut": "actif"
    },
    {
        "id": "5005",
        "nom": "GRAND REPLOMB",
        "code": "5005",
        "commune": "SAINT-MURY-MONTEYMONT",
        "code_postal": "38190",
        "activite": "parapente  [ déco ]",
        "statut": "actif"
    },
    {
        "id": "3022",
        "nom": "GRANGE DU MURE",
        "code": "3022",
        "commune": "CLAIX",
        "code_postal": "38640",
        "activite": "parapente  [ déco ]",
        "statut": "actif"
    },
    {
        "id": "196",
        "nom": "JAS D 'ORIS",
        "code": "196",
        "commune": "ORIS EN RATTIER",
        "code_postal": "38350",
        "activite": "parapente delta  [ atterro ]",
        "statut": "actif"
    },
    {
        "id": "195",
        "nom": "JAS D 'ORIS - LES FOND PLAINES",
        "code": "195",
        "commune": "ORIS EN RATTIER",
        "code_postal": "38350",
        "activite": "parapente delta  [ déco ]",
        "statut": "actif"
    },
    {
        "id": "1038",
        "nom": "L 'ALEVOUX",
        "code": "1038",
        "commune": "ST PIERRE DE CHERENNES",
        "code_postal": "38160",
        "activite": "parapente delta  [ déco ]",
        "statut": "actif"
    },
    {
        "id": "1039",
        "nom": "L 'ALEVOUX",
        "code": "1039",
        "commune": "ST PIERRE DE CHERENNES",
        "code_postal": "38160",
        "activite": "parapente delta  [ atterro ]",
        "statut": "actif"
    },
    {
        "id": "5071",
        "nom": "LA GRANDE SURE",
        "code": "5071",
        "commune": "SAINT-JULIEN-DE-RAZ",
        "code_postal": "38134",
        "activite": "parapente  [ déco ]",
        "statut": "actif"
    },
    {
        "id": "135",
        "nom": "LA LIA",
        "code": "135",
        "commune": "MALLEVAL EN VERCORS",
        "code_postal": "38470",
        "activite": "parapente  [ déco ]",
        "statut": "actif"
    },
    {
        "id": "1630",
        "nom": "LA PLAINE - KITE",
        "code": "1630",
        "commune": "AUTRANS",
        "code_postal": "38880",
        "activite": "snowkite",
        "statut": "non praticable définitivement"
    },
    {
        "id": "2227",
        "nom": "LA PLAINE (AUTRANS)",
        "code": "2227",
        "commune": "AUTRANS",
        "code_postal": "38880",
        "activite": "snowkite",
        "statut": "actif"
    },
    {
        "id": "1021",
        "nom": "LA SARNA",
        "code": "1021",
        "commune": "LA CHAPELLE EN VERCORS",
        "code_postal": "38???",
        "activite": "parapente delta  [ atterro ]",
        "statut": "non praticable définitivement"
    },
    {
        "id": "3148",
        "nom": "LA VILLE",
        "code": "3148",
        "commune": "MONTEYNARD",
        "code_postal": "38770",
        "activite": "parapente  [ atterro ]",
        "statut": "actif"
    },
    {
        "id": "5305",
        "nom": "LAC DE CROP",
        "code": "5305",
        "commune": "LAVAL",
        "code_postal": "38190",
        "activite": "parapente  [ atterro ]",
        "statut": "actif"
    },
    {
        "id": "1647",
        "nom": "LAFFREY",
        "code": "1647",
        "commune": "ST BARTHELEMY-DE-SECHILIENNE",
        "code_postal": "38220",
        "activite": "parapente delta  [ atterro ]",
        "statut": "actif"
    },
    {
        "id": "1821",
        "nom": "LAFFREY - LES FAURIES",
        "code": "1821",
        "commune": "LAFFREY",
        "code_postal": "38220",
        "activite": "parapente  [ déco ]",
        "statut": "actif"
    },
    {
        "id": "1646",
        "nom": "LAFFREY - LIEU DIT",
        "code": "1646",
        "commune": "LAFFREY",
        "code_postal": "38220",
        "activite": "parapente  [ déco ]",
        "statut": "non praticable définitivement"
    },
    {
        "id": "1241",
        "nom": "LANS-EN-VERCORS",
        "code": "1241",
        "commune": "LANS-EN-VERCORS",
        "code_postal": "38250",
        "activite": "parapente  [ atterro ]",
        "statut": "actif"
    },
    {
        "id": "1238",
        "nom": "LANS-EN-VERCORS - DENT PERCEE",
        "code": "1238",
        "commune": "LANS-EN-VERCORS",
        "code_postal": "38250",
        "activite": "parapente  [ déco ]",
        "statut": "actif"
    },
    {
        "id": "1240",
        "nom": "LANS-EN-VERCORS - LA 7",
        "code": "1240",
        "commune": "LANS-EN-VERCORS",
        "code_postal": "38250",
        "activite": "parapente  [ déco ]",
        "statut": "actif"
    },
    {
        "id": "5300",
        "nom": "LE CHATEL",
        "code": "5300",
        "commune": "CORDEAC",
        "code_postal": "38710",
        "activite": "parapente  [ déco ]",
        "statut": "actif"
    },
    {
        "id": "13721",
        "nom": "LE COMBENON - T^TE DE VACHE",
        "code": "13721",
        "commune": "SAINT AREY",
        "code_postal": "38350",
        "activite": "parapente  [ atterro ]",
        "statut": "actif"
    },
    {
        "id": "13720",
        "nom": "LE COMBENON - TETE DE VACHE",
        "code": "13720",
        "commune": "SAINT AREY",
        "code_postal": "38350",
        "activite": "parapente  [ déco ]",
        "statut": "actif"
    },
    {
        "id": "1214",
        "nom": "LE GRAND RATZ",
        "code": "1214",
        "commune": "LA BUISSE",
        "code_postal": "38500",
        "activite": "parapente delta  [ déco ]",
        "statut": "actif"
    },
    {
        "id": "1215",
        "nom": "LE GRAND RATZ",
        "code": "1215",
        "commune": "LA BUISSE",
        "code_postal": "38500",
        "activite": "parapente delta  [ atterro ]",
        "statut": "actif"
    },
    {
        "id": "1911",
        "nom": "LE GRAND RATZ",
        "code": "1911",
        "commune": "LA BUISSE",
        "code_postal": "38500",
        "activite": "parapente delta  [ atterro ]",
        "statut": "actif"
    },
    {
        "id": "3142",
        "nom": "LE SAPPEY-EN-CHARTREUSE",
        "code": "3142",
        "commune": "LE SAPPEY-EN-CHARTREUSE",
        "code_postal": "38700",
        "activite": "parapente  [ atterro ]",
        "statut": "actif"
    },
    {
        "id": "1232",
        "nom": "LE SERPATON - COL DU FAU",
        "code": "1232",
        "commune": "SAINT-PAUL-LES-MONESTIER",
        "code_postal": "38650",
        "activite": "parapente delta  [ atterro ]",
        "statut": "actif"
    },
    {
        "id": "1235",
        "nom": "LE SERPATON EST - LE PAS DU SERPATON",
        "code": "1235",
        "commune": "ST PAUL LES MONESTIERS",
        "code_postal": "38650",
        "activite": "parapente delta  [ déco ]",
        "statut": "actif"
    },
    {
        "id": "1233",
        "nom": "LE SERPATON INTERMEDAIRE - OUEST",
        "code": "1233",
        "commune": "GRESSE EN VERCORS",
        "code_postal": "38650",
        "activite": "parapente  [ déco ]",
        "statut": "actif"
    },
    {
        "id": "1234",
        "nom": "LE SERPATON OUEST 500",
        "code": "1234",
        "commune": "GRESSE EN VERCORS",
        "code_postal": "38650",
        "activite": "parapente  [ déco ]",
        "statut": "actif"
    },
    {
        "id": "1242",
        "nom": "LES 2 ALPES",
        "code": "1242",
        "commune": "VENOSC",
        "code_postal": "38860",
        "activite": "parapente speedriding  [ atterro ]",
        "statut": "actif"
    },
    {
        "id": "1243",
        "nom": "LES 2 ALPES - LE DIABLE",
        "code": "1243",
        "commune": "VENOSC",
        "code_postal": "38860",
        "activite": "parapente speedriding  [ déco ]",
        "statut": "actif"
    },
    {
        "id": "13104",
        "nom": "LES 2 ALPES - LES PERRONS",
        "code": "13104",
        "commune": "VENOSC",
        "code_postal": "38860",
        "activite": "parapente delta  [ déco ]",
        "statut": "actif"
    },
    {
        "id": "1245",
        "nom": "LES 2 ALPES - VENOSC",
        "code": "1245",
        "commune": "VENOSC",
        "code_postal": "38860",
        "activite": "parapente speedriding  [ atterro ]",
        "statut": "actif"
    },
    {
        "id": "5276",
        "nom": "LES BANNETTES",
        "code": "5276",
        "commune": "MONT-SAINT-MARTIN",
        "code_postal": "38120",
        "activite": "parapente  [ déco ]",
        "statut": "actif"
    },
    {
        "id": "2348",
        "nom": "LES FALKEN",
        "code": "2348",
        "commune": "ALPE D'HUEZ",
        "code_postal": "38750",
        "activite": "speedriding  [ ]",
        "statut": "actif"
    },
    {
        "id": "2349",
        "nom": "LES PLATES - LES PLATES",
        "code": "2349",
        "commune": "ALPE D'HUEZ",
        "code_postal": "38750",
        "activite": "speedriding  [ ]",
        "statut": "actif"
    },
    {
        "id": "1236",
        "nom": "LES RIVIERES",
        "code": "1236",
        "commune": "GRESSE EN VERCORS",
        "code_postal": "38650",
        "activite": "parapente  [ atterro ]",
        "statut": "actif"
    },
    {
        "id": "1878",
        "nom": "LES SEPT LAUX - SPEED-RIDING",
        "code": "1878",
        "commune": "LES ADRETS",
        "code_postal": "38190",
        "activite": "speedriding  [ ]",
        "statut": "actif"
    },
    {
        "id": "3009",
        "nom": "LES SOUILLETS",
        "code": "3009",
        "commune": "SAINT-BARTHELEMY-DE-SECHILIENNE",
        "code_postal": "38220",
        "activite": "parapente  [ déco ]",
        "statut": "actif"
    },
    {
        "id": "1881",
        "nom": "LEYRIEU",
        "code": "1881",
        "commune": "LEYRIEU",
        "code_postal": "38460",
        "activite": "parapente delta  [ atterro ]",
        "statut": "actif"
    },
    {
        "id": "1880",
        "nom": "LEYRIEU - LES COTTES",
        "code": "1880",
        "commune": "LEYRIEU",
        "code_postal": "38460",
        "activite": "parapente delta  [ déco ]",
        "statut": "interdit"
    },
    {
        "id": "1107",
        "nom": "MALLEVAL - LA LUNETTE",
        "code": "1107",
        "commune": "MALLEVAL",
        "code_postal": "38470",
        "activite": "parapente  [ déco ]",
        "statut": "non praticable définitivement"
    },
    {
        "id": "134",
        "nom": "MALLEVAL - PAS DE L 'ANE",
        "code": "134",
        "commune": "MALLEVAL",
        "code_postal": "38470",
        "activite": "parapente  [ atterro ]",
        "statut": "actif"
    },
    {
        "id": "13562",
        "nom": "MALLEVAL - PAS DE L 'ANE",
        "code": "13562",
        "commune": "MALLEVAL",
        "code_postal": "38470",
        "activite": "parapente  [ déco ]",
        "statut": "actif"
    },
    {
        "id": "953",
        "nom": "MEAUDRE - LE CRET",
        "code": "953",
        "commune": "MEAUDRE",
        "code_postal": "38112",
        "activite": "parapente  [ déco ]",
        "statut": "actif"
    },
    {
        "id": "954",
        "nom": "MEAUDRE - LES FARLAIX",
        "code": "954",
        "commune": "MEAUDRE",
        "code_postal": "38112",
        "activite": "parapente  [ atterro ]",
        "statut": "actif"
    },
    {
        "id": "1216",
        "nom": "MONTAUD",
        "code": "1216",
        "commune": "MONTAUD",
        "code_postal": "38500",
        "activite": "parapente delta  [ déco ]",
        "statut": "actif"
    },
    {
        "id": "1217",
        "nom": "MONTAUD",
        "code": "1217",
        "commune": "MONTAUD",
        "code_postal": "38500",
        "activite": "parapente delta  [ atterro ]",
        "statut": "actif"
    },
    {
        "id": "5262",
        "nom": "MOUCHEROTTE (N)",
        "code": "5262",
        "commune": "SAINT-NIZIER-DU-MOUCHEROTTE",
        "code_postal": "38250",
        "activite": "parapente  [ déco ]",
        "statut": "actif"
    },
    {
        "id": "5261",
        "nom": "PAS DE L 'OEILLE",
        "code": "5261",
        "commune": "LE GUA",
        "code_postal": "38450",
        "activite": "parapente  [ déco ]",
        "statut": "actif"
    },
    {
        "id": "658",
        "nom": "PERQUELIN",
        "code": "658",
        "commune": "ST PIERRE DE CHARTREUSE",
        "code_postal": "38380",
        "activite": "parapente delta  [ atterro ]",
        "statut": "actif"
    },
    {
        "id": "5092",
        "nom": "PETIT MONTAUD",
        "code": "5092",
        "commune": "SAINT-QUENTIN-SUR-ISERE",
        "code_postal": "38210",
        "activite": "parapente  [ déco ]",
        "statut": "actif"
    },
    {
        "id": "3042",
        "nom": "PIC SAINT-MICHEL",
        "code": "3042",
        "commune": "SAINT-PAUL-DE-VARCES",
        "code_postal": "38760",
        "activite": "parapente  [ déco ]",
        "statut": "actif"
    },
    {
        "id": "1741",
        "nom": "PIERRE PLANTEE - TREUIL",
        "code": "1741",
        "commune": "LA MOTTE D'AVEILLANS",
        "code_postal": "38770",
        "activite": "snowkite",
        "statut": "non praticable définitivement"
    },
    {
        "id": "1804",
        "nom": "PISTE BLANCHOT - SPEED-RIDING",
        "code": "1804",
        "commune": "LE COLLET D'ALLEVARD",
        "code_postal": "38580",
        "activite": "speedriding  [ ]",
        "statut": "actif"
    },
    {
        "id": "2347",
        "nom": "PISTE DE BOB - PISTE DE BOB",
        "code": "2347",
        "commune": "ALPE D'HUEZ",
        "code_postal": "38750",
        "activite": "speedriding  [ ]",
        "statut": "actif"
    },
    {
        "id": "13597",
        "nom": "PLAGE NORD",
        "code": "13597",
        "commune": "TREFFORT",
        "code_postal": "38650",
        "activite": "kitesurf (kite eau)",
        "statut": "actif"
    },
    {
        "id": "5291",
        "nom": "PLATEAU DU CORNAFION",
        "code": "5291",
        "commune": "SAINT-PAUL-DE-VARCES",
        "code_postal": "38760",
        "activite": "parapente  [ déco ]",
        "statut": "actif"
    },
    {
        "id": "13474",
        "nom": "POISAT",
        "code": "13474",
        "commune": "POISAT",
        "code_postal": "38320",
        "activite": "parapente  [ déco ]",
        "statut": "actif"
    },
    {
        "id": "1478",
        "nom": "PRAPOUTEL LES 7 LAUX",
        "code": "1478",
        "commune": "PRAPOUTEL - LES 7 LAUX",
        "code_postal": "38190",
        "activite": "parapente  [ atterro ]",
        "statut": "actif"
    },
    {
        "id": "1374",
        "nom": "PRAPOUTEL LES 7 LAUX - LA JASSE",
        "code": "1374",
        "commune": "PRAPOUTEL - LES 7 LAUX",
        "code_postal": "38190",
        "activite": "parapente  [ déco ]",
        "statut": "actif"
    },
    {
        "id": "3070",
        "nom": "ROCHASSAC",
        "code": "3070",
        "commune": "SAINT-BAUDILLE-ET-PIPET",
        "code_postal": "38710",
        "activite": "parapente  [ déco ]",
        "statut": "actif"
    },
    {
        "id": "1247",
        "nom": "SAINT HILAIRE DU TOUVET",
        "code": "1247",
        "commune": "SAINT HILAIRE DU TOUVET",
        "code_postal": "38660",
        "activite": "parapente  [ atterro pente école ]",
        "statut": "actif"
    },
    {
        "id": "1249",
        "nom": "SAINT HILAIRE DU TOUVET - CHALET MOQUETTE",
        "code": "1249",
        "commune": "SAINT HILAIRE DU TOUVET",
        "code_postal": "38660",
        "activite": "parapente  [ déco ]",
        "statut": "actif"
    },
    {
        "id": "1255",
        "nom": "SAINT HILAIRE DU TOUVET - DENT DE CROLLES",
        "code": "1255",
        "commune": "ST PIERRE DE CHARTREUSE",
        "code_postal": "38380",
        "activite": "parapente  [ déco ]",
        "statut": "actif"
    },
    {
        "id": "1254",
        "nom": "SAINT HILAIRE DU TOUVET - LUMBIN 2",
        "code": "1254",
        "commune": "LUMBIN",
        "code_postal": "38660",
        "activite": "delta  [ atterro ]",
        "statut": "actif autorisation systematique requise"
    },
    {
        "id": "1253",
        "nom": "SAINT HILAIRE DU TOUVET - LUMBIN CIBLE",
        "code": "1253",
        "commune": "LUMBIN",
        "code_postal": "38660",
        "activite": "parapente  [ atterro ]",
        "statut": "actif"
    },
    {
        "id": "13604",
        "nom": "SAINT HILAIRE DU TOUVET - LUMBUN - DELTA",
        "code": "13604",
        "commune": "LUMBIN",
        "code_postal": "38660",
        "activite": "delta  [ atterro ]",
        "statut": "actif"
    },
    {
        "id": "1250",
        "nom": "SAINT HILAIRE DU TOUVET - PRAVOUTA",
        "code": "1250",
        "commune": "SAINT PIERRE DE CHARTREUSE",
        "code_postal": "38380",
        "activite": "parapente  [ déco ]",
        "statut": "actif"
    },
    {
        "id": "1252",
        "nom": "SAINT HILAIRE DU TOUVET - SAINT HIL 1",
        "code": "1252",
        "commune": "ST HILAIRE DU TOUVET",
        "code_postal": "38660",
        "activite": "delta  [ atterro ]",
        "statut": "actif"
    },
    {
        "id": "1251",
        "nom": "SAINT HILAIRE DU TOUVET - SAINT-NAZAIRE-LES-EYMES",
        "code": "1251",
        "commune": "ST NAZAIRE LES EYMES",
        "code_postal": "38660",
        "activite": "parapente  [ atterro ]",
        "statut": "actif"
    },
    {
        "id": "1248",
        "nom": "SAINT HILAIRE DU TOUVET - SUD",
        "code": "1248",
        "commune": "SAINT HILAIRE DU TOUVET",
        "code_postal": "38660",
        "activite": "parapente delta  [ déco ]",
        "statut": "actif"
    },
    {
        "id": "1246",
        "nom": "SAINT HILAIRE DU TOUVET - TREMPLIN SAPINIERE",
        "code": "1246",
        "commune": "SAINT HILAIRE DU TOUVET",
        "code_postal": "38660",
        "activite": "delta  [ déco ]",
        "statut": "actif"
    },
    {
        "id": "13279",
        "nom": "SAINT HILAIRE DU TOUVET FUNICULAIRE - EST",
        "code": "13279",
        "commune": "SAINT HILAIRE DU TOUVET",
        "code_postal": "38660",
        "activite": "parapente delta  [ déco ]",
        "statut": "actif"
    },
    {
        "id": "13287",
        "nom": "SAINT HUGUES - ST HUGUES",
        "code": "13287",
        "commune": "ST PIERRE DE CHARTREUSE",
        "code_postal": "38380",
        "activite": "parapente delta  [ atterro ]",
        "statut": "actif"
    },
    {
        "id": "687",
        "nom": "SAINT PIERRE D 'ALLEVARD - LA CHAPELLE SAINT CHRISTOPHE",
        "code": "687",
        "commune": "ST PIERRE D'ALLEVARD",
        "code_postal": "38830",
        "activite": "parapente delta  [ déco ]",
        "statut": "actif"
    },
    {
        "id": "688",
        "nom": "SAINT PIERRE D 'ALLEVARD - SAINT-PIERRE D 'ALLEVARD",
        "code": "688",
        "commune": "ST PIERRE D'ALLEVARD",
        "code_postal": "38830",
        "activite": "parapente delta  [ atterro ]",
        "statut": "actif"
    },
    {
        "id": "657",
        "nom": "SAINT PIERRE DE CHARTREUSE - LA SCIA - LUCHERON",
        "code": "657",
        "commune": "ST PIERRE DE CHARTREUSE",
        "code_postal": "38380",
        "activite": "parapente delta  [ déco ]",
        "statut": "actif"
    },
    {
        "id": "1794",
        "nom": "SAINT-HILAIRE - SPEED-RIDING",
        "code": "1794",
        "commune": "SAINT HILAIRE DU TOUVET",
        "code_postal": "38660",
        "activite": "parapente delta speedriding  [ ]",
        "statut": "actif"
    },
    {
        "id": "3122",
        "nom": "SAINT-NIZIER",
        "code": "3122",
        "commune": "SAINT-MARTIN-D'URIAGE",
        "code_postal": "38410",
        "activite": "parapente  [ atterro ]",
        "statut": "interdit"
    },
    {
        "id": "2346",
        "nom": "SARRASINS - PRABUTIN",
        "code": "2346",
        "commune": "ALPE D'HUEZ",
        "code_postal": "38750",
        "activite": "speedriding  [ ]",
        "statut": "actif"
    },
    {
        "id": "3115",
        "nom": "SECHILIENNE",
        "code": "3115",
        "commune": "SECHILIENNE",
        "code_postal": "38220",
        "activite": "parapente  [ atterro ]",
        "statut": "actif"
    },
    {
        "id": "3135",
        "nom": "ST NIZIER MOUCHEROTTES",
        "code": "3135",
        "commune": "SAINT-NIZIER-DU-MOUCHEROTTE",
        "code_postal": "38250",
        "activite": "parapente  [ atterro ]",
        "statut": "actif"
    },
    {
        "id": "3126",
        "nom": "STADE DE CLAIX",
        "code": "3126",
        "commune": "VARCES-ALLIERES-ET-RISSET",
        "code_postal": "38760",
        "activite": "parapente  [ atterro ]",
        "statut": "actif"
    },
    {
        "id": "13372",
        "nom": "TELECABINE COTE2000",
        "code": "13372",
        "commune": "VILLARD DE LANS",
        "code_postal": "38250",
        "activite": "parapente  [ atterro ]",
        "statut": "actif"
    },
    {
        "id": "5238",
        "nom": "TETE DE L 'OBIOU",
        "code": "5238",
        "commune": "SAINT-BAUDILLE-ET-PIPET",
        "code_postal": "38710",
        "activite": "parapente  [ déco ]",
        "statut": "actif"
    },
    {
        "id": "1257",
        "nom": "VARCES",
        "code": "1257",
        "commune": "ST PAUL DE VARCES",
        "code_postal": "38660",
        "activite": "parapente  [ atterro ]",
        "statut": "actif"
    },
    {
        "id": "1256",
        "nom": "VARCES - PLATEAU DE SAINT ANGE",
        "code": "1256",
        "commune": "VARCES",
        "code_postal": "38660",
        "activite": "parapente  [ déco ]",
        "statut": "actif"
    },
    {
        "id": "1258",
        "nom": "VARCES - PRE DU FOUR",
        "code": "1258",
        "commune": "VARCES",
        "code_postal": "38760",
        "activite": "parapente  [ déco ]",
        "statut": "actif"
    },
    {
        "id": "315",
        "nom": "VILLARD - COTE 2000",
        "code": "315",
        "commune": "VILLARD DE LANS",
        "code_postal": "38250",
        "activite": "parapente  [ atterro ]",
        "statut": "non praticable définitivement"
    },
    {
        "id": "13507",
        "nom": "VILLARD REYMOND - VILLARD REYMOND",
        "code": "13507",
        "commune": "VILLARD REYMOND",
        "code_postal": "38520",
        "activite": "parapente  [ déco ]",
        "statut": "actif"
    },
    {
        "id": "3136",
        "nom": "VILLARD SAINT-CHRISTOPHE",
        "code": "3136",
        "commune": "VILLARD-SAINT-CHRISTOPHE",
        "code_postal": "38119",
        "activite": "parapente  [ atterro ]",
        "statut": "actif"
    },
    {
        "id": "13504",
        "nom": "ZONE KITE - BASE FFVL DE LUMBIN",
        "code": "13504",
        "commune": "LUMBIN",
        "code_postal": "38660",
        "activite": "cerf-volant boomerang",
        "statut": "actif"
    }
]